pyssp_standard/__init__.py
pyssp_standard/common_content_ssc.py
pyssp_standard/fmu.py
pyssp_standard/parameter_types.py
pyssp_standard/srmd.py
pyssp_standard/ssb.py
pyssp_standard/ssd.py
pyssp_standard/ssm.py
pyssp_standard/ssp.py
pyssp_standard/ssv.py
pyssp_standard/standard.py
pyssp_standard/transformation_types.py
pyssp_standard/unit.py
pyssp_standard/unit_conversion.py
pyssp_standard/utils.py
pyssp_standard/resources/SRMD11.xsd
pyssp_standard/resources/STC11.xsd
pyssp_standard/resources/SystemStructureCommon.xsd
pyssp_standard/resources/SystemStructureDescription.xsd
pyssp_standard/resources/SystemStructureDescription11.xsd
pyssp_standard/resources/SystemStructureParameterMapping.xsd
pyssp_standard/resources/SystemStructureParameterValues.xsd
pyssp_standard/resources/SystemStructureSignalDictionary.xsd
pyssp_standard/resources/fmi30/fmi3Annotation.xsd
pyssp_standard/resources/fmi30/fmi3AttributeGroups.xsd
pyssp_standard/resources/fmi30/fmi3BuildDescription.xsd
pyssp_standard/resources/fmi30/fmi3InterfaceType.xsd
pyssp_standard/resources/fmi30/fmi3LayeredStandardManifest.xsd
pyssp_standard/resources/fmi30/fmi3ModelDescription.xsd
pyssp_standard/resources/fmi30/fmi3Terminal.xsd
pyssp_standard/resources/fmi30/fmi3TerminalsAndIcons.xsd
pyssp_standard/resources/fmi30/fmi3Type.xsd
pyssp_standard/resources/fmi30/fmi3Unit.xsd
pyssp_standard/resources/fmi30/fmi3Variable.xsd
pyssp_standard/resources/fmi30/fmi3VariableDependency.xsd
pyssp_standard-0.8.2.dist-info/licenses/LICENSE
pyssp_standard-0.8.2.dist-info/METADATA
pyssp_standard-0.8.2.dist-info/WHEEL
pyssp_standard-0.8.2.dist-info/top_level.txt
pyssp_standard-0.8.2.dist-info/RECORD
