Metadata-Version: 2.4
Name: pyssp_standard
Version: 0.8.2
Summary: Simple python package for reading, modifying and creating files, specified in the SSP Standard
Home-page: https://github.com/FGHaider/pyssp
Download-URL: https://github.com/FGHaider/pyssp/archive/refs/tags/v_01.tar.gz
Author: Fredrik Haider
Author-email: 
License: MIT
Keywords: SSP,system,engineering
Classifier: Development Status :: 3 - Alpha
Classifier: Intended Audience :: Developers
Classifier: Topic :: Software Development :: Build Tools
Classifier: License :: OSI Approved :: MIT License
Classifier: Programming Language :: Python :: 3
Classifier: Programming Language :: Python :: 3.10
Classifier: Programming Language :: Python :: 3.11
License-File: LICENSE
Requires-Dist: lxml
Requires-Dist: xmlschema
Requires-Dist: pint
Dynamic: author
Dynamic: classifier
Dynamic: description-content-type
Dynamic: download-url
Dynamic: home-page
Dynamic: keywords
Dynamic: license
Dynamic: license-file
Dynamic: requires-dist
Dynamic: summary
